fpboost/__init__.py
fpboost/models.py
fpboost/test_models.py
fpboost-0.1.0.dist-info/LICENSE
fpboost-0.1.0.dist-info/METADATA
fpboost-0.1.0.dist-info/WHEEL
fpboost-0.1.0.dist-info/RECORD
