Metadata-Version: 2.1
Name: fpboost
Version: 0.1.0
Summary: FPBoost: a gradient boosting model for survival analysis that builds hazard functions as a combination of fully parametric hazards.
License: MIT
Author: Alberto Archetti
Author-email: alberto.archetti@polimi.it
Requires-Python: >=3.10.0,<3.13.0
Classifier: License :: OSI Approved :: MIT License
Classifier: Programming Language :: Python :: 3
Classifier: Programming Language :: Python :: 3.10
Classifier: Programming Language :: Python :: 3.11
Requires-Dist: numpy (>=1.26.4,<2.0.0)
Requires-Dist: pandas (>=2.2.1,<3.0.0)
Requires-Dist: scikit-survival (>=0.22.2,<0.23.0)
Requires-Dist: torch (>=2.3.1,<3.0.0)
Requires-Dist: urllib3 (>=1.26.8,<2.0.0)
